defijn_integrations/__init__.py
defijn_integrations/clickupint.py
defijn_integrations/everhourint.py
defijn_integrations/gitlabint.py
defijn_integrations-0.1.2.dist-info/METADATA
defijn_integrations-0.1.2.dist-info/WHEEL
defijn_integrations-0.1.2.dist-info/entry_points.txt
defijn_integrations-0.1.2.dist-info/RECORD
