Metadata-Version: 2.1
Name: defijn-integrations
Version: 0.1.2
Summary: Defijn's package providing integrations for various third-party APIs such as Everhour, GitLab and Clickup.
Home-page: https://defijn.io
License: MIT
Author: Jonathan
Author-email: jonathan@defijn.io
Requires-Python: >=3.11,<4.0
Classifier: License :: OSI Approved :: MIT License
Classifier: Programming Language :: Python :: 3
Classifier: Programming Language :: Python :: 3.11
Requires-Dist: python-gitlab (>=4.4.0,<5.0.0)
Requires-Dist: questionary (>=2.0.1,<3.0.0)
Requires-Dist: requests (>=2.31.0,<3.0.0)
Requires-Dist: rich (>=13.7.0,<14.0.0)
Requires-Dist: textual (>=0.58.0,<0.59.0)
Requires-Dist: twine (>=5.0.0,<6.0.0)
Project-URL: Repository, https://github.com/defijn-io/defijn-integrations
